{"data_mtime":1689521747,"dep_lines":[24,31,21,28,34,1,2,3,4,5,8,11,18,1,1,1,1,1,1,1,1,1,1],"dep_prios":[5,5,5,5,5,10,10,10,10,5,5,5,5,5,30,30,30,30,30,30,30,30,30],"dependencies":["websockets.legacy.client","web3.providers.base","websockets.client","web3.exceptions","web3.types","asyncio","json","logging","os","threading","types","typing","eth_typing","builtins","abc","asyncio.events","asyncio.protocols","eth_typing.ethpm","eth_utils","eth_utils.exceptions","websockets","websockets.legacy","websockets.legacy.protocol"],"hash":"4bcbfc1c3d81dd8b5f7568a7a0592225322ee23edc5862e2006dce840bdef571","id":"web3.providers.websocket","ignore_all":true,"interface_hash":"539b82d4474c5725e05e96f9b70e6e0dcd8384bf70a908e65abbbebc71bf9acc","mtime":1688754290,"options":{"allow_redefinition":false,"allow_untyped_globals":false,"always_false":[],"always_true":[],"bazel":false,"check_untyped_defs":false,"disable_bytearray_promotion":false,"disable_error_code":[],"disable_memoryview_promotion":false,"disabled_error_codes":[],"disallow_any_decorated":false,"disallow_any_explicit":false,"disallow_any_expr":false,"disallow_any_generics":false,"disallow_any_unimported":false,"disallow_incomplete_defs":false,"disallow_subclassing_any":false,"disallow_untyped_calls":false,"disallow_untyped_decorators":false,"disallow_untyped_defs":false,"enable_error_code":[],"enabled_error_codes":[],"follow_imports":"silent","follow_imports_for_stubs":false,"ignore_errors":false,"ignore_missing_imports":true,"implicit_optional":false,"implicit_reexport":true,"local_partial_types":false,"mypyc":false,"platform":"darwin","plugins":[],"strict_concatenate":false,"strict_equality":false,"strict_optional":true,"warn_no_return":true,"warn_return_any":false,"warn_unreachable":false,"warn_unused_ignores":false},"path":"/Users/coccoinomane/code/web3/airfarm/.venv/lib/python3.10/site-packages/web3/providers/websocket.py","plugin_data":null,"size":3919,"suppressed":[],"version_id":"1.4.1"}